datatableview/__init__.py
datatableview/forms.py
datatableview/helpers.py
datatableview/models.py
datatableview/utils.py
datatableview/views.py
datatableview/static/js/datatableview.js
datatableview/static/js/datatableview.min.js
datatableview/templates/datatableview/bootstrap_structure.html
datatableview/templates/datatableview/default_structure.html
datatableview/tests/__init__.py
datatableview/tests/test_helpers.py
datatableview/tests/test_utils.py
datatableview/tests/test_views.py
datatableview/tests/testcase.py
datatableview/tests/example_project/__init__.py
datatableview/tests/example_project/manage.py
datatableview/tests/example_project/example_project/__init__.py
datatableview/tests/example_project/example_project/settings.py
datatableview/tests/example_project/example_project/urls.py
datatableview/tests/example_project/example_project/wsgi.py
datatableview/tests/example_project/example_project/example_app/__init__.py
datatableview/tests/example_project/example_project/example_app/models.py
datatableview/tests/example_project/example_project/example_app/urls.py
datatableview/tests/example_project/example_project/example_app/views.py
datatableview/tests/example_project/example_project/example_app/migrations/0001_initial.py
datatableview/tests/example_project/example_project/example_app/migrations/__init__.py
datatableview/tests/example_project/example_project/example_app/templatetags/__init__.py
datatableview/tests/test_app/__init__.py
datatableview/tests/test_app/models.py
django_datatable_view_compat-0.8.7.dist-info/LICENSE.txt
django_datatable_view_compat-0.8.7.dist-info/METADATA
django_datatable_view_compat-0.8.7.dist-info/WHEEL
django_datatable_view_compat-0.8.7.dist-info/top_level.txt
django_datatable_view_compat-0.8.7.dist-info/RECORD
