Metadata-Version: 2.1
Name: django-datatable-view-compat
Version: 0.8.7
Summary: This package is used in conjunction with the jQuery plugin (http://http://datatables.net/), and supports state-saving detection with (http://datatables.net/plug-ins/api).  The package consists of a class-based view, and a small collection of utilities for rendering table data from models.
Home-page: https://github.com/utapyngo/django-datatable-view
Author: utapyngo
Author-email: ut@pyngo.tom.ru
License: Apache License (2.0)
Download-URL: https://github.com/utapyngo/django-datatable-view/tarball/django20
Platform: UNKNOWN
Classifier: Development Status :: 2 - Pre-Alpha
Classifier: Environment :: Web Environment
Classifier: Framework :: Django
Classifier: Intended Audience :: Developers
Classifier: License :: OSI Approved :: Apache Software License
Classifier: Operating System :: OS Independent
Classifier: Programming Language :: Python
Classifier: Topic :: Software Development
Requires-Dist: django (>=2.0)
Requires-Dist: python-dateutil (>=2.1)
